seml/__init__.py
seml/__main__.py
seml/database.py
seml/document.py
seml/evaluation.py
seml/settings.py
seml/cli_utils/__init__.py
seml/cli_utils/cache.py
seml/cli_utils/cli_states.py
seml/cli_utils/module_hider.py
seml/cli_utils/typer.py
seml/commands/__init__.py
seml/commands/add.py
seml/commands/configure.py
seml/commands/description.py
seml/commands/manage.py
seml/commands/migration.py
seml/commands/print.py
seml/commands/project.py
seml/commands/slurm.py
seml/commands/sources.py
seml/commands/start.py
seml/console/__init__.py
seml/experiment/__init__.py
seml/experiment/command.py
seml/experiment/config.py
seml/experiment/description.py
seml/experiment/experiment.py
seml/experiment/mattermost_observer.py
seml/experiment/observers.py
seml/experiment/parameters.py
seml/experiment/sources.py
seml/templates/slurm/jupyter_template.sh
seml/templates/slurm/slurm_template.sh
seml/utils/__init__.py
seml/utils/errors.py
seml/utils/io.py
seml/utils/json.py
seml/utils/multi_process.py
seml/utils/network.py
seml/utils/slurm.py
seml/utils/ssh_forward.py
seml/utils/yaml.py
seml-0.5.4.dist-info/METADATA
seml-0.5.4.dist-info/WHEEL
seml-0.5.4.dist-info/entry_points.txt
seml-0.5.4.dist-info/licenses/LICENSE
seml-0.5.4.dist-info/RECORD
