Metadata-Version: 2.3
Name: seml
Version: 0.5.4
Summary: Slurm Experiment Management Library
Project-URL: Homepage, https://github.com/TUM-DAML/seml
Project-URL: Documentation, https://github.com/TUM-DAML/seml/blob/master/docs.md
Project-URL: Repository, https://github.com/TUM-DAML/seml
Project-URL: Changelog, https://github.com/TUM-DAML/seml/releases/latest
Author: DAML Group @ TUM
Author-email: Daniel Zügner <zuegnerd@in.tum.de>, Johannes Gsteiger <johannes.gasteiger@tum.de>, Nicholas Gao <n.gao@tum.de>, Dominik Fuchsgruber <d.fuchsgruber@tum.de>
Maintainer-email: Nicholas Gao <n.gao@tum.de>, Dominik Fuchsgruber <d.fuchsgruber@tum.de>
License: MIT License
License-File: LICENSE
Classifier: Programming Language :: Python
Requires-Python: >=3.10
Requires-Dist: debugpy>=1.2.1
Requires-Dist: deepdiff>=7.0.1
Requires-Dist: gitignore-parser>=0.1.11
Requires-Dist: importlib-resources>=5.7.0
Requires-Dist: jsonpickle>=2.2
Requires-Dist: munch>=4.0
Requires-Dist: numpy>=1.15; python_version < '3.13'
Requires-Dist: numpy>=2.1; python_version >= '3.13'
Requires-Dist: omegaconf>=2.3.0
Requires-Dist: pandas>=2.2
Requires-Dist: pymongo>=4.1
Requires-Dist: pyyaml>=5.1
Requires-Dist: requests>=2.28.1
Requires-Dist: rich>=13.0
Requires-Dist: sacred>=0.8.4
Requires-Dist: setuptools>=69.2.0
Requires-Dist: typer>=0.12
Requires-Dist: typing-extensions>=4.10; python_version < '3.13'
Requires-Dist: typing-extensions>=4.12; python_version >= '3.13'
Provides-Extra: dev
Requires-Dist: filelock>=3.15.4; extra == 'dev'
Requires-Dist: pre-commit>=3.8.0; extra == 'dev'
Requires-Dist: pytest>=8.3.2; extra == 'dev'
Requires-Dist: ruff>=0.6.1; extra == 'dev'
Requires-Dist: sshtunnel>=0.4.0; extra == 'dev'
Provides-Extra: ssh-forward
Requires-Dist: filelock>=3.13.3; extra == 'ssh-forward'
Requires-Dist: sshtunnel>=0.4.0; extra == 'ssh-forward'
